python_dev_docker_project/__init__.py
python_dev_docker_project/__main__.py
python_dev_docker_project/hello.py
python_dev_docker_project/tests/__init__.py
python_dev_docker_project/tests/test_hello.py
python_dev_docker_project/tests/test_main.py
python_dev_docker_project-0.5.4.dev0.dist-info/LICENSE
python_dev_docker_project-0.5.4.dev0.dist-info/METADATA
python_dev_docker_project-0.5.4.dev0.dist-info/WHEEL
python_dev_docker_project-0.5.4.dev0.dist-info/entry_points.txt
python_dev_docker_project-0.5.4.dev0.dist-info/top_level.txt
python_dev_docker_project-0.5.4.dev0.dist-info/RECORD
