Metadata-Version: 2.1
Name: python-dev-docker-project
Version: 0.5.4.dev0
Summary: UNKNOWN
Home-page: https://github.com/gtesei/Patterns_for_Continuous_Integration_Docker_Travis_CI_2_DEV
Author: Gino Tesei
Author-email: 
License: BSD-3-Clause
Platform: UNKNOWN
Classifier: Development Status :: 3 - Alpha
Classifier: License :: OSI Approved :: BSD License
Classifier: Programming Language :: Python :: 3.6
